localport/__init__.py
localport/__main__.py
localport/daemon.py
localport/main.py
localport/application/__init__.py
localport/application/dto/__init__.py
localport/application/dto/connection_dto.py
localport/application/dto/health_dto.py
localport/application/dto/service_dto.py
localport/application/services/__init__.py
localport/application/services/cluster_config_manager.py
localport/application/services/cluster_health_manager.py
localport/application/services/configuration_differ.py
localport/application/services/configuration_manager.py
localport/application/services/configuration_watcher.py
localport/application/services/connection_discovery_service.py
localport/application/services/connection_validation_service.py
localport/application/services/daemon_manager.py
localport/application/services/health_monitor.py
localport/application/services/health_monitor_scheduler.py
localport/application/services/restart_manager.py
localport/application/services/service_manager.py
localport/application/use_cases/__init__.py
localport/application/use_cases/add_connection.py
localport/application/use_cases/list_connections.py
localport/application/use_cases/manage_daemon.py
localport/application/use_cases/monitor_services.py
localport/application/use_cases/remove_connection.py
localport/application/use_cases/start_services.py
localport/application/use_cases/stop_services.py
localport/cli/__init__.py
localport/cli/app.py
localport/cli/commands/__init__.py
localport/cli/commands/cluster_commands.py
localport/cli/commands/config_commands.py
localport/cli/commands/daemon_commands.py
localport/cli/commands/log_commands.py
localport/cli/commands/service_commands.py
localport/cli/commands/ssh_commands.py
localport/cli/commands/version_command.py
localport/cli/formatters/__init__.py
localport/cli/formatters/connection_formatter.py
localport/cli/formatters/format_router.py
localport/cli/formatters/json_formatter.py
localport/cli/formatters/output_format.py
localport-1.0.0.dist-info/licenses/LICENSE
localport-1.0.0.dist-info/METADATA
localport-1.0.0.dist-info/WHEEL
localport-1.0.0.dist-info/entry_points.txt
localport-1.0.0.dist-info/top_level.txt
localport-1.0.0.dist-info/RECORD
