Metadata-Version: 2.4
Name: localport
Version: 1.0.0
Summary: Universal port forwarding manager with health monitoring
Author: Larry Dawson
License: MIT License
Project-URL: Homepage, https://github.com/dawsonlp/localport
Project-URL: Repository, https://github.com/dawsonlp/localport
Project-URL: Documentation, https://github.com/dawsonlp/localport#readme
Project-URL: Bug Tracker, https://github.com/dawsonlp/localport/issues
Classifier: Development Status :: 4 - Beta
Classifier: Environment :: Console
Classifier: Intended Audience :: Developers
Classifier: License :: OSI Approved :: MIT License
Classifier: Operating System :: OS Independent
Classifier: Programming Language :: Python :: 3
Classifier: Programming Language :: Python :: 3.11
Classifier: Programming Language :: Python :: 3.12
Classifier: Programming Language :: Python :: 3.13
Classifier: Topic :: Software Development
Classifier: Topic :: System :: Networking
Requires-Python: >=3.11
License-File: LICENSE
Requires-Dist: typer>=0.12.0
Requires-Dist: rich>=13.7.0
Requires-Dist: pydantic>=2.8.0
Requires-Dist: pydantic-settings>=2.4.0
Requires-Dist: pyyaml>=6.0.1
Requires-Dist: aiohttp>=3.9.0
Requires-Dist: psutil>=5.9.0
Requires-Dist: structlog>=24.1.0
Requires-Dist: tenacity>=8.2.0
Requires-Dist: click>=8.1.0
Requires-Dist: watchdog>=3.0.0
Provides-Extra: dev
Requires-Dist: pytest>=8.0.0; extra == "dev"
Requires-Dist: pytest-asyncio>=0.23.0; extra == "dev"
Requires-Dist: pytest-cov>=4.0.0; extra == "dev"
Requires-Dist: pytest-mock>=3.12.0; extra == "dev"
Requires-Dist: black>=24.0.0; extra == "dev"
Requires-Dist: ruff>=0.5.0; extra == "dev"
Requires-Dist: mypy>=1.10.0; extra == "dev"
Requires-Dist: pre-commit>=3.7.0; extra == "dev"
Requires-Dist: pytest-xdist>=3.5.0; extra == "dev"
Provides-Extra: kafka
Requires-Dist: kafka-python>=2.0.2; extra == "kafka"
Provides-Extra: postgres
Requires-Dist: psycopg[binary]>=3.2.0; extra == "postgres"
Provides-Extra: all
Requires-Dist: localport[kafka,postgres]; extra == "all"
Dynamic: license-file
